horriblesubs_downloader/__init__.py
horriblesubs_downloader/__main__.py
horriblesubs_downloader/downloader.py
horriblesubs_downloader/error.py
horriblesubs_downloader/scraper.py
horriblesubs_downloader-1.0.1.dist-info/METADATA
horriblesubs_downloader-1.0.1.dist-info/RECORD
horriblesubs_downloader-1.0.1.dist-info/WHEEL
horriblesubs_downloader-1.0.1.dist-info/entry_points.txt
horriblesubs_downloader-1.0.1.dist-info/top_level.txt
