Metadata-Version: 2.1
Name: horriblesubs-downloader
Version: 1.0.1
Summary: A simple anime torrent downloader.
Home-page: https://github.com/nadyafebi/horriblesubs_downloader
Author: Nadya Djojosantoso
Author-email: hello@nadyafebi.com
License: UNKNOWN
Platform: UNKNOWN
Classifier: Programming Language :: Python :: 3
Classifier: License :: OSI Approved :: MIT License
Classifier: Operating System :: OS Independent
Requires-Dist: docopt
Requires-Dist: configparser
Requires-Dist: clint
Requires-Dist: selenium
